django_dd_logger/__init__.py
django_dd_logger/celery.py
django_dd_logger/encoders.py
django_dd_logger/local.py
django_dd_logger/recursion.py
django_dd_logger/wsgi.py
django_dd_logger/formatters/__init__.py
django_dd_logger/formatters/datadog.py
django_dd_logger/middleware/__init__.py
django_dd_logger/middleware/error_log.py
django_dd_logger/middleware/request_id.py
django_dd_logger/middleware/request_log.py
django_dd_logger-0.7.1.dist-info/AUTHORS.rst
django_dd_logger-0.7.1.dist-info/LICENSE
django_dd_logger-0.7.1.dist-info/METADATA
django_dd_logger-0.7.1.dist-info/WHEEL
django_dd_logger-0.7.1.dist-info/top_level.txt
django_dd_logger-0.7.1.dist-info/RECORD
