Metadata-Version: 2.1
Name: django_dd_logger
Version: 0.7.1
Summary: Django logging utilities for Datadog
Author-email: Jacek Broński-Jankowski <contact@jankow.ski>
License: MIT
Project-URL: Homepage, https://github.com/jacekbj/django-dd-logger
Project-URL: Bug Tracker, https://github.com/jacekbj/django-dd-logger/issues
Keywords: django,logging,datadog,logging middleware
Classifier: Development Status :: 3 - Alpha
Classifier: Intended Audience :: Developers
Classifier: License :: OSI Approved :: MIT License
Classifier: Operating System :: OS Independent
Classifier: Natural Language :: English
Classifier: Programming Language :: Python :: 3
Classifier: Programming Language :: Python :: 3.7
Classifier: Programming Language :: Python :: 3.8
Classifier: Programming Language :: Python :: 3.9
Classifier: Programming Language :: Python :: 3.10
Classifier: Programming Language :: Python :: 3.11
Classifier: Programming Language :: Python :: 3.12
Requires-Python: >=3.7
License-File: LICENSE
License-File: AUTHORS.rst
Requires-Dist: JSON-log-formatter
Requires-Dist: Django <5 ; python_version < "3.10"
Requires-Dist: Django ; python_version >= "3.10"
Provides-Extra: build
Requires-Dist: build ; extra == 'build'
Requires-Dist: setuptools-scm ==8.* ; extra == 'build'
Requires-Dist: twine ==4.* ; extra == 'build'
Requires-Dist: wheel ==0.42.* ; extra == 'build'
Provides-Extra: dev
Requires-Dist: coverage ==7.* ; extra == 'dev'
Requires-Dist: setuptools ; extra == 'dev'
Requires-Dist: ruff ; extra == 'dev'
Provides-Extra: docs
Requires-Dist: Sphinx ==7.* ; extra == 'docs'
